{"nodes":[{"id":"core_readme_core","label":"core 导读","file_type":"document","source_file":"src/MapLibre/core/README.md","source_location":null,"source_url":null,"captured_at":null,"author":null,"contributor":null},{"id":"core_core_module","label":"core 模块","file_type":"rationale","source_file":"src/MapLibre/core/README.md","source_location":null,"source_url":null,"captured_at":null,"author":null,"contributor":null},{"id":"core_map_host_orchestration","label":"地图宿主编排","file_type":"rationale","source_file":"src/MapLibre/core/README.md","source_location":null,"source_url":null,"captured_at":null,"author":null,"contributor":null},{"id":"core_map_init","label":"地图初始化","file_type":"rationale","source_file":"src/MapLibre/core/README.md","source_location":null,"source_url":null,"captured_at":null,"author":null,"contributor":null},{"id":"core_plugin_host","label":"插件宿主","file_type":"rationale","source_file":"src/MapLibre/core/README.md","source_location":null,"source_url":null,"captured_at":null,"author":null,"contributor":null},{"id":"core_control_lifecycle","label":"控件生命周期","file_type":"rationale","source_file":"src/MapLibre/core/README.md","source_location":null,"source_url":null,"captured_at":null,"author":null,"contributor":null},{"id":"core_external_expose","label":"对外 expose","file_type":"rationale","source_file":"src/MapLibre/core/README.md","source_location":null,"source_url":null,"captured_at":null,"author":null,"contributor":null},{"id":"core_maplibre_init_vue","label":"mapLibre-init.vue","file_type":"code","source_file":"src/MapLibre/core/README.md","source_location":null,"source_url":null,"captured_at":null,"author":null,"contributor":null},{"id":"core_maplibre_init_types","label":"mapLibre-init.types.ts","file_type":"code","source_file":"src/MapLibre/core/README.md","source_location":null,"source_url":null,"captured_at":null,"author":null,"contributor":null},{"id":"core_use_map_plugin_host","label":"useMapPluginHost.ts","file_type":"code","source_file":"src/MapLibre/core/README.md","source_location":null,"source_url":null,"captured_at":null,"author":null,"contributor":null},{"id":"core_use_terradraw_control_lifecycle","label":"useTerradrawControlLifecycle.ts","file_type":"code","source_file":"src/MapLibre/core/README.md","source_location":null,"source_url":null,"captured_at":null,"author":null,"contributor":null},{"id":"core_mgl_popup","label":"mgl-popup.vue","file_type":"code","source_file":"src/MapLibre/core/README.md","source_location":null,"source_url":null,"captured_at":null,"author":null,"contributor":null},{"id":"core_map_instance_creation","label":"地图实例创建","file_type":"rationale","source_file":"src/MapLibre/core/README.md","source_location":null,"source_url":null,"captured_at":null,"author":null,"contributor":null},{"id":"core_root_component_expose","label":"根组件暴露能力","file_type":"rationale","source_file":"src/MapLibre/core/README.md","source_location":null,"source_url":null,"captured_at":null,"author":null,"contributor":null},{"id":"core_terradraw_measure_control","label":"TerraDraw / Measure 控件","file_type":"rationale","source_file":"src/MapLibre/core/README.md","source_location":null,"source_url":null,"captured_at":null,"author":null,"contributor":null},{"id":"facades_readme_facades","label":"facades 导读","file_type":"document","source_file":"src/MapLibre/facades/README.md","source_location":null,"source_url":null,"captured_at":null,"author":null,"contributor":null},{"id":"facades_facades_module","label":"facades 模块","file_type":"rationale","source_file":"src/MapLibre/facades/README.md","source_location":null,"source_url":null,"captured_at":null,"author":null,"contributor":null},{"id":"facades_business_facade","label":"高层业务门面","file_type":"rationale","source_file":"src/MapLibre/facades/README.md","source_location":null,"source_url":null,"captured_at":null,"author":null,"contributor":null},{"id":"facades_business_query_edit_action","label":"业务查询编辑动作","file_type":"rationale","source_file":"src/MapLibre/facades/README.md","source_location":null,"source_url":null,"captured_at":null,"author":null,"contributor":null},{"id":"facades_source_organization","label":"source 组织能力","file_type":"rationale","source_file":"src/MapLibre/facades/README.md","source_location":null,"source_url":null,"captured_at":null,"author":null,"contributor":null},{"id":"facades_stable_entry","label":"稳定入口","file_type":"rationale","source_file":"src/MapLibre/facades/README.md","source_location":null,"source_url":null,"captured_at":null,"author":null,"contributor":null},{"id":"facades_use_business_map","label":"useBusinessMap.ts","file_type":"code","source_file":"src/MapLibre/facades/README.md","source_location":null,"source_url":null,"captured_at":null,"author":null,"contributor":null},{"id":"facades_create_map_business_source","label":"createMapBusinessSource.ts","file_type":"code","source_file":"src/MapLibre/facades/README.md","source_location":null,"source_url":null,"captured_at":null,"author":null,"contributor":null},{"id":"facades_map_business_layer","label":"mapBusinessLayer.ts","file_type":"code","source_file":"src/MapLibre/facades/README.md","source_location":null,"source_url":null,"captured_at":null,"author":null,"contributor":null},{"id":"facades_use_map_feature_query","label":"useMapFeatureQuery.ts","file_type":"code","source_file":"src/MapLibre/facades/README.md","source_location":null,"source_url":null,"captured_at":null,"author":null,"contributor":null},{"id":"facades_use_map_feature_actions","label":"useMapFeatureActions.ts","file_type":"code","source_file":"src/MapLibre/facades/README.md","source_location":null,"source_url":null,"captured_at":null,"author":null,"contributor":null},{"id":"facades_use_map_feature_property_editor","label":"useMapFeaturePropertyEditor.ts","file_type":"code","source_file":"src/MapLibre/facades/README.md","source_location":null,"source_url":null,"captured_at":null,"author":null,"contributor":null},{"id":"facades_map_plugin_resolver","label":"mapPluginResolver.ts","file_type":"code","source_file":"src/MapLibre/facades/README.md","source_location":null,"source_url":null,"captured_at":null,"author":null,"contributor":null},{"id":"facades_plugin_api_reading","label":"插件 API 读取","file_type":"rationale","source_file":"src/MapLibre/facades/README.md","source_location":null,"source_url":null,"captured_at":null,"author":null,"contributor":null},{"id":"plugins_readme_plugins","label":"plugins 导读","file_type":"document","source_file":"src/MapLibre/plugins/README.md","source_location":null,"source_url":null,"captured_at":null,"author":null,"contributor":null},{"id":"plugins_plugins_module","label":"plugins 模块","file_type":"rationale","source_file":"src/MapLibre/plugins/README.md","source_location":null,"source_url":null,"captured_at":null,"author":null,"contributor":null},{"id":"plugins_internal_implementation","label":"插件内部实现","file_type":"rationale","source_file":"src/MapLibre/plugins/README.md","source_location":null,"source_url":null,"captured_at":null,"author":null,"contributor":null},{"id":"plugins_public_entries","label":"src/plugins/*.ts","file_type":"code","source_file":"src/MapLibre/plugins/README.md","source_location":null,"source_url":null,"captured_at":null,"author":null,"contributor":null},{"id":"plugins_types","label":"types.ts","file_type":"code","source_file":"src/MapLibre/plugins/README.md","source_location":null,"source_url":null,"captured_at":null,"author":null,"contributor":null},{"id":"plugins_plugin_contract","label":"插件系统公共契约","file_type":"rationale","source_file":"src/MapLibre/plugins/README.md","source_location":null,"source_url":null,"captured_at":null,"author":null,"contributor":null},{"id":"plugins_plugin_index","label":"各插件目录 index.ts","file_type":"code","source_file":"src/MapLibre/plugins/README.md","source_location":null,"source_url":null,"captured_at":null,"author":null,"contributor":null},{"id":"plugins_use_plugin","label":"各插件目录 use*Plugin.ts","file_type":"code","source_file":"src/MapLibre/plugins/README.md","source_location":null,"source_url":null,"captured_at":null,"author":null,"contributor":null},{"id":"plugins_controller_service_store","label":"controller service store","file_type":"code","source_file":"src/MapLibre/plugins/README.md","source_location":null,"source_url":null,"captured_at":null,"author":null,"contributor":null},{"id":"plugins_line_draft_preview","label":"line-draft-preview","file_type":"code","source_file":"src/MapLibre/plugins/README.md","source_location":null,"source_url":null,"captured_at":null,"author":null,"contributor":null},{"id":"plugins_map_feature_snap","label":"map-feature-snap","file_type":"code","source_file":"src/MapLibre/plugins/README.md","source_location":null,"source_url":null,"captured_at":null,"author":null,"contributor":null},{"id":"plugins_map_feature_multi_select","label":"map-feature-multi-select","file_type":"code","source_file":"src/MapLibre/plugins/README.md","source_location":null,"source_url":null,"captured_at":null,"author":null,"contributor":null},{"id":"plugins_intersection_preview","label":"intersection-preview","file_type":"code","source_file":"src/MapLibre/plugins/README.md","source_location":null,"source_url":null,"captured_at":null,"author":null,"contributor":null},{"id":"plugins_map_dxf_export","label":"map-dxf-export","file_type":"code","source_file":"src/MapLibre/plugins/README.md","source_location":null,"source_url":null,"captured_at":null,"author":null,"contributor":null},{"id":"plugins_plugin_state_interaction_rendering","label":"插件状态交互渲染","file_type":"rationale","source_file":"src/MapLibre/plugins/README.md","source_location":null,"source_url":null,"captured_at":null,"author":null,"contributor":null},{"id":"terradraw_readme_terradraw","label":"terradraw 导读","file_type":"document","source_file":"src/MapLibre/terradraw/README.md","source_location":null,"source_url":null,"captured_at":null,"author":null,"contributor":null},{"id":"terradraw_terradraw_module","label":"terradraw 模块","file_type":"rationale","source_file":"src/MapLibre/terradraw/README.md","source_location":null,"source_url":null,"captured_at":null,"author":null,"contributor":null},{"id":"terradraw_integration","label":"TerraDraw 集成实现","file_type":"rationale","source_file":"src/MapLibre/terradraw/README.md","source_location":null,"source_url":null,"captured_at":null,"author":null,"contributor":null},{"id":"terradraw_mode_config","label":"模式配置","file_type":"rationale","source_file":"src/MapLibre/terradraw/README.md","source_location":null,"source_url":null,"captured_at":null,"author":null,"contributor":null},{"id":"terradraw_interaction_bridge","label":"交互桥接","file_type":"rationale","source_file":"src/MapLibre/terradraw/README.md","source_location":null,"source_url":null,"captured_at":null,"author":null,"contributor":null},{"id":"terradraw_snap_sync_concept","label":"吸附同步","file_type":"rationale","source_file":"src/MapLibre/terradraw/README.md","source_location":null,"source_url":null,"captured_at":null,"author":null,"contributor":null},{"id":"terradraw_line_decoration","label":"线装饰渲染","file_type":"rationale","source_file":"src/MapLibre/terradraw/README.md","source_location":null,"source_url":null,"captured_at":null,"author":null,"contributor":null},{"id":"terradraw_terradraw_config","label":"terradraw-config.ts","file_type":"code","source_file":"src/MapLibre/terradraw/README.md","source_location":null,"source_url":null,"captured_at":null,"author":null,"contributor":null},{"id":"terradraw_mode_factory","label":"terradraw-mode-factory.ts","file_type":"code","source_file":"src/MapLibre/terradraw/README.md","source_location":null,"source_url":null,"captured_at":null,"author":null,"contributor":null},{"id":"terradraw_use_interactive","label":"useTerradrawInteractive.ts","file_type":"code","source_file":"src/MapLibre/terradraw/README.md","source_location":null,"source_url":null,"captured_at":null,"author":null,"contributor":null},{"id":"terradraw_snap_sync","label":"terradraw-snap-sync.ts","file_type":"code","source_file":"src/MapLibre/terradraw/README.md","source_location":null,"source_url":null,"captured_at":null,"author":null,"contributor":null},{"id":"terradraw_use_line_decoration","label":"useTerradrawLineDecoration.ts","file_type":"code","source_file":"src/MapLibre/terradraw/README.md","source_location":null,"source_url":null,"captured_at":null,"author":null,"contributor":null},{"id":"terradraw_line_decoration_layers","label":"TerradrawLineDecorationLayers.vue","file_type":"code","source_file":"src/MapLibre/terradraw/README.md","source_location":null,"source_url":null,"captured_at":null,"author":null,"contributor":null},{"id":"terradraw_default_mode_config","label":"TerraDraw 默认模式和配置","file_type":"rationale","source_file":"src/MapLibre/terradraw/README.md","source_location":null,"source_url":null,"captured_at":null,"author":null,"contributor":null},{"id":"terradraw_draw_result_action","label":"绘制结果业务动作","file_type":"rationale","source_file":"src/MapLibre/terradraw/README.md","source_location":null,"source_url":null,"captured_at":null,"author":null,"contributor":null}],"edges":[{"source":"core_readme_core","target":"core_core_module","relation":"references","confidence":"EXTRACTED","confidence_score":1.0,"source_file":"src/MapLibre/core/README.md","source_location":null,"weight":1.0},{"source":"core_core_module","target":"core_map_host_orchestration","relation":"conceptually_related_to","confidence":"EXTRACTED","confidence_score":1.0,"source_file":"src/MapLibre/core/README.md","source_location":null,"weight":1.0},{"source":"core_core_module","target":"core_map_init","relation":"conceptually_related_to","confidence":"EXTRACTED","confidence_score":1.0,"source_file":"src/MapLibre/core/README.md","source_location":null,"weight":1.0},{"source":"core_core_module","target":"core_plugin_host","relation":"conceptually_related_to","confidence":"EXTRACTED","confidence_score":1.0,"source_file":"src/MapLibre/core/README.md","source_location":null,"weight":1.0},{"source":"core_core_module","target":"core_control_lifecycle","relation":"conceptually_related_to","confidence":"EXTRACTED","confidence_score":1.0,"source_file":"src/MapLibre/core/README.md","source_location":null,"weight":1.0},{"source":"core_core_module","target":"core_external_expose","relation":"conceptually_related_to","confidence":"EXTRACTED","confidence_score":1.0,"source_file":"src/MapLibre/core/README.md","source_location":null,"weight":1.0},{"source":"core_maplibre_init_vue","target":"core_map_host_orchestration","relation":"implements","confidence":"EXTRACTED","confidence_score":1.0,"source_file":"src/MapLibre/core/README.md","source_location":null,"weight":1.0},{"source":"core_maplibre_init_vue","target":"core_map_instance_creation","relation":"implements","confidence":"EXTRACTED","confidence_score":1.0,"source_file":"src/MapLibre/core/README.md","source_location":null,"weight":1.0},{"source":"core_maplibre_init_vue","target":"core_external_expose","relation":"implements","confidence":"INFERRED","confidence_score":0.8,"source_file":"src/MapLibre/core/README.md","source_location":null,"weight":1.0},{"source":"core_maplibre_init_types","target":"core_root_component_expose","relation":"implements","confidence":"EXTRACTED","confidence_score":1.0,"source_file":"src/MapLibre/core/README.md","source_location":null,"weight":1.0},{"source":"core_use_map_plugin_host","target":"core_plugin_host","relation":"implements","confidence":"EXTRACTED","confidence_score":1.0,"source_file":"src/MapLibre/core/README.md","source_location":null,"weight":1.0},{"source":"core_use_map_plugin_host","target":"plugins_plugins_module","relation":"references","confidence":"EXTRACTED","confidence_score":1.0,"source_file":"src/MapLibre/core/README.md","source_location":null,"weight":1.0},{"source":"core_use_terradraw_control_lifecycle","target":"core_terradraw_measure_control","relation":"implements","confidence":"EXTRACTED","confidence_score":1.0,"source_file":"src/MapLibre/core/README.md","source_location":null,"weight":1.0},{"source":"core_use_terradraw_control_lifecycle","target":"core_control_lifecycle","relation":"implements","confidence":"EXTRACTED","confidence_score":1.0,"source_file":"src/MapLibre/core/README.md","source_location":null,"weight":1.0},{"source":"core_mgl_popup","target":"core_core_module","relation":"conceptually_related_to","confidence":"EXTRACTED","confidence_score":1.0,"source_file":"src/MapLibre/core/README.md","source_location":null,"weight":1.0},{"source":"core_core_module","target":"facades_facades_module","relation":"references","confidence":"EXTRACTED","confidence_score":1.0,"source_file":"src/MapLibre/core/README.md","source_location":null,"weight":1.0},{"source":"core_core_module","target":"plugins_plugins_module","relation":"references","confidence":"EXTRACTED","confidence_score":1.0,"source_file":"src/MapLibre/core/README.md","source_location":null,"weight":1.0},{"source":"core_core_module","target":"terradraw_terradraw_module","relation":"references","confidence":"EXTRACTED","confidence_score":1.0,"source_file":"src/MapLibre/core/README.md","source_location":null,"weight":1.0},{"source":"facades_readme_facades","target":"facades_facades_module","relation":"references","confidence":"EXTRACTED","confidence_score":1.0,"source_file":"src/MapLibre/facades/README.md","source_location":null,"weight":1.0},{"source":"facades_facades_module","target":"facades_business_facade","relation":"conceptually_related_to","confidence":"EXTRACTED","confidence_score":1.0,"source_file":"src/MapLibre/facades/README.md","source_location":null,"weight":1.0},{"source":"facades_business_facade","target":"facades_business_query_edit_action","relation":"conceptually_related_to","confidence":"EXTRACTED","confidence_score":1.0,"source_file":"src/MapLibre/facades/README.md","source_location":null,"weight":1.0},{"source":"facades_business_facade","target":"facades_source_organization","relation":"conceptually_related_to","confidence":"EXTRACTED","confidence_score":1.0,"source_file":"src/MapLibre/facades/README.md","source_location":null,"weight":1.0},{"source":"facades_business_facade","target":"facades_stable_entry","relation":"rationale_for","confidence":"EXTRACTED","confidence_score":1.0,"source_file":"src/MapLibre/facades/README.md","source_location":null,"weight":1.0},{"source":"facades_use_business_map","target":"facades_business_facade","relation":"implements","confidence":"EXTRACTED","confidence_score":1.0,"source_file":"src/MapLibre/facades/README.md","source_location":null,"weight":1.0},{"source":"facades_create_map_business_source","target":"facades_source_organization","relation":"implements","confidence":"EXTRACTED","confidence_score":1.0,"source_file":"src/MapLibre/facades/README.md","source_location":null,"weight":1.0},{"source":"facades_map_business_layer","target":"facades_source_organization","relation":"conceptually_related_to","confidence":"EXTRACTED","confidence_score":1.0,"source_file":"src/MapLibre/facades/README.md","source_location":null,"weight":1.0},{"source":"facades_use_map_feature_query","target":"facades_business_query_edit_action","relation":"implements","confidence":"EXTRACTED","confidence_score":1.0,"source_file":"src/MapLibre/facades/README.md","source_location":null,"weight":1.0},{"source":"facades_use_map_feature_actions","target":"facades_business_query_edit_action","relation":"implements","confidence":"EXTRACTED","confidence_score":1.0,"source_file":"src/MapLibre/facades/README.md","source_location":null,"weight":1.0},{"source":"facades_use_map_feature_property_editor","target":"facades_business_query_edit_action","relation":"implements","confidence":"EXTRACTED","confidence_score":1.0,"source_file":"src/MapLibre/facades/README.md","source_location":null,"weight":1.0},{"source":"facades_map_plugin_resolver","target":"facades_plugin_api_reading","relation":"implements","confidence":"EXTRACTED","confidence_score":1.0,"source_file":"src/MapLibre/facades/README.md","source_location":null,"weight":1.0},{"source":"facades_business_facade","target":"plugins_plugins_module","relation":"references","confidence":"EXTRACTED","confidence_score":1.0,"source_file":"src/MapLibre/facades/README.md","source_location":null,"weight":1.0},{"source":"facades_business_facade","target":"core_core_module","relation":"references","confidence":"EXTRACTED","confidence_score":1.0,"source_file":"src/MapLibre/facades/README.md","source_location":null,"weight":1.0},{"source":"facades_business_facade","target":"terradraw_terradraw_module","relation":"references","confidence":"EXTRACTED","confidence_score":1.0,"source_file":"src/MapLibre/facades/README.md","source_location":null,"weight":1.0},{"source":"plugins_readme_plugins","target":"plugins_plugins_module","relation":"references","confidence":"EXTRACTED","confidence_score":1.0,"source_file":"src/MapLibre/plugins/README.md","source_location":null,"weight":1.0},{"source":"plugins_plugins_module","target":"plugins_internal_implementation","relation":"conceptually_related_to","confidence":"EXTRACTED","confidence_score":1.0,"source_file":"src/MapLibre/plugins/README.md","source_location":null,"weight":1.0},{"source":"plugins_plugins_module","target":"plugins_public_entries","relation":"references","confidence":"EXTRACTED","confidence_score":1.0,"source_file":"src/MapLibre/plugins/README.md","source_location":null,"weight":1.0},{"source":"plugins_types","target":"plugins_plugin_contract","relation":"implements","confidence":"EXTRACTED","confidence_score":1.0,"source_file":"src/MapLibre/plugins/README.md","source_location":null,"weight":1.0},{"source":"plugins_plugin_index","target":"plugins_internal_implementation","relation":"implements","confidence":"EXTRACTED","confidence_score":1.0,"source_file":"src/MapLibre/plugins/README.md","source_location":null,"weight":1.0},{"source":"plugins_use_plugin","target":"plugins_internal_implementation","relation":"implements","confidence":"EXTRACTED","confidence_score":1.0,"source_file":"src/MapLibre/plugins/README.md","source_location":null,"weight":1.0},{"source":"plugins_use_plugin","target":"facades_plugin_api_reading","relation":"shares_data_with","confidence":"INFERRED","confidence_score":0.75,"source_file":"src/MapLibre/plugins/README.md","source_location":null,"weight":1.0},{"source":"plugins_controller_service_store","target":"plugins_plugin_state_interaction_rendering","relation":"implements","confidence":"EXTRACTED","confidence_score":1.0,"source_file":"src/MapLibre/plugins/README.md","source_location":null,"weight":1.0},{"source":"plugins_line_draft_preview","target":"plugins_internal_implementation","relation":"implements","confidence":"EXTRACTED","confidence_score":1.0,"source_file":"src/MapLibre/plugins/README.md","source_location":null,"weight":1.0},{"source":"plugins_map_feature_snap","target":"plugins_internal_implementation","relation":"implements","confidence":"EXTRACTED","confidence_score":1.0,"source_file":"src/MapLibre/plugins/README.md","source_location":null,"weight":1.0},{"source":"plugins_map_feature_multi_select","target":"plugins_internal_implementation","relation":"implements","confidence":"EXTRACTED","confidence_score":1.0,"source_file":"src/MapLibre/plugins/README.md","source_location":null,"weight":1.0},{"source":"plugins_intersection_preview","target":"plugins_internal_implementation","relation":"implements","confidence":"EXTRACTED","confidence_score":1.0,"source_file":"src/MapLibre/plugins/README.md","source_location":null,"weight":1.0},{"source":"plugins_map_dxf_export","target":"plugins_internal_implementation","relation":"implements","confidence":"EXTRACTED","confidence_score":1.0,"source_file":"src/MapLibre/plugins/README.md","source_location":null,"weight":1.0},{"source":"plugins_plugins_module","target":"core_use_map_plugin_host","relation":"references","confidence":"EXTRACTED","confidence_score":1.0,"source_file":"src/MapLibre/plugins/README.md","source_location":null,"weight":1.0},{"source":"plugins_plugins_module","target":"facades_map_plugin_resolver","relation":"references","confidence":"EXTRACTED","confidence_score":1.0,"source_file":"src/MapLibre/plugins/README.md","source_location":null,"weight":1.0},{"source":"terradraw_readme_terradraw","target":"terradraw_terradraw_module","relation":"references","confidence":"EXTRACTED","confidence_score":1.0,"source_file":"src/MapLibre/terradraw/README.md","source_location":null,"weight":1.0},{"source":"terradraw_terradraw_module","target":"terradraw_integration","relation":"conceptually_related_to","confidence":"EXTRACTED","confidence_score":1.0,"source_file":"src/MapLibre/terradraw/README.md","source_location":null,"weight":1.0},{"source":"terradraw_integration","target":"terradraw_mode_config","relation":"conceptually_related_to","confidence":"EXTRACTED","confidence_score":1.0,"source_file":"src/MapLibre/terradraw/README.md","source_location":null,"weight":1.0},{"source":"terradraw_integration","target":"terradraw_interaction_bridge","relation":"conceptually_related_to","confidence":"EXTRACTED","confidence_score":1.0,"source_file":"src/MapLibre/terradraw/README.md","source_location":null,"weight":1.0},{"source":"terradraw_integration","target":"terradraw_snap_sync_concept","relation":"conceptually_related_to","confidence":"EXTRACTED","confidence_score":1.0,"source_file":"src/MapLibre/terradraw/README.md","source_location":null,"weight":1.0},{"source":"terradraw_integration","target":"terradraw_line_decoration","relation":"conceptually_related_to","confidence":"EXTRACTED","confidence_score":1.0,"source_file":"src/MapLibre/terradraw/README.md","source_location":null,"weight":1.0},{"source":"terradraw_terradraw_config","target":"terradraw_default_mode_config","relation":"implements","confidence":"EXTRACTED","confidence_score":1.0,"source_file":"src/MapLibre/terradraw/README.md","source_location":null,"weight":1.0},{"source":"terradraw_terradraw_config","target":"terradraw_mode_config","relation":"implements","confidence":"EXTRACTED","confidence_score":1.0,"source_file":"src/MapLibre/terradraw/README.md","source_location":null,"weight":1.0},{"source":"terradraw_mode_factory","target":"terradraw_mode_config","relation":"implements","confidence":"EXTRACTED","confidence_score":1.0,"source_file":"src/MapLibre/terradraw/README.md","source_location":null,"weight":1.0},{"source":"terradraw_use_interactive","target":"terradraw_interaction_bridge","relation":"implements","confidence":"EXTRACTED","confidence_score":1.0,"source_file":"src/MapLibre/terradraw/README.md","source_location":null,"weight":1.0},{"source":"terradraw_snap_sync","target":"terradraw_snap_sync_concept","relation":"implements","confidence":"EXTRACTED","confidence_score":1.0,"source_file":"src/MapLibre/terradraw/README.md","source_location":null,"weight":1.0},{"source":"terradraw_snap_sync","target":"plugins_map_feature_snap","relation":"shares_data_with","confidence":"EXTRACTED","confidence_score":1.0,"source_file":"src/MapLibre/terradraw/README.md","source_location":null,"weight":1.0},{"source":"terradraw_use_line_decoration","target":"terradraw_line_decoration","relation":"implements","confidence":"EXTRACTED","confidence_score":1.0,"source_file":"src/MapLibre/terradraw/README.md","source_location":null,"weight":1.0},{"source":"terradraw_line_decoration_layers","target":"terradraw_line_decoration","relation":"implements","confidence":"EXTRACTED","confidence_score":1.0,"source_file":"src/MapLibre/terradraw/README.md","source_location":null,"weight":1.0},{"source":"terradraw_terradraw_module","target":"core_use_terradraw_control_lifecycle","relation":"references","confidence":"EXTRACTED","confidence_score":1.0,"source_file":"src/MapLibre/terradraw/README.md","source_location":null,"weight":1.0},{"source":"terradraw_terradraw_module","target":"facades_use_map_feature_actions","relation":"references","confidence":"EXTRACTED","confidence_score":1.0,"source_file":"src/MapLibre/terradraw/README.md","source_location":null,"weight":1.0},{"source":"facades_use_map_feature_actions","target":"terradraw_draw_result_action","relation":"implements","confidence":"INFERRED","confidence_score":0.75,"source_file":"src/MapLibre/terradraw/README.md","source_location":null,"weight":1.0},{"source":"core_use_map_plugin_host","target":"plugins_plugin_contract","relation":"shares_data_with","confidence":"INFERRED","confidence_score":0.85,"source_file":"src/MapLibre/plugins/README.md","source_location":null,"weight":1.0},{"source":"facades_map_plugin_resolver","target":"plugins_plugin_contract","relation":"shares_data_with","confidence":"INFERRED","confidence_score":0.8,"source_file":"src/MapLibre/facades/README.md","source_location":null,"weight":1.0},{"source":"terradraw_use_interactive","target":"core_map_host_orchestration","relation":"shares_data_with","confidence":"INFERRED","confidence_score":0.7,"source_file":"src/MapLibre/terradraw/README.md","source_location":null,"weight":1.0}],"hyperedges":[{"id":"business_facade_pattern","label":"业务门面收口模式","nodes":["facades_use_business_map","facades_create_map_business_source","facades_map_business_layer","facades_use_map_feature_query","facades_use_map_feature_actions","facades_use_map_feature_property_editor","facades_map_plugin_resolver"],"relation":"form","confidence":"EXTRACTED","confidence_score":1.0,"source_file":"src/MapLibre/facades/README.md"},{"id":"plugin_runtime_pattern","label":"插件运行时模式","nodes":["plugins_types","plugins_plugin_index","plugins_use_plugin","plugins_controller_service_store","core_use_map_plugin_host","facades_map_plugin_resolver"],"relation":"form","confidence":"INFERRED","confidence_score":0.85,"source_file":"src/MapLibre/plugins/README.md"},{"id":"terradraw_integration_flow","label":"TerraDraw 集成流程","nodes":["terradraw_terradraw_config","terradraw_mode_factory","terradraw_use_interactive","terradraw_snap_sync","terradraw_use_line_decoration","terradraw_line_decoration_layers","core_use_terradraw_control_lifecycle"],"relation":"form","confidence":"EXTRACTED","confidence_score":1.0,"source_file":"src/MapLibre/terradraw/README.md"}],"input_tokens":0,"output_tokens":0}
